docs/docs/safire/__init__.py
docs/docs/safire/constants.py
docs/docs/safire/utils.py
docs/docs/safire/evaluation/__init__.py
docs/docs/safire/evaluation/core.py
docs/docs/safire/evaluation/datasets.py
docs/docs/safire/evaluation/judge.py
docs/docs/safire/evaluation/render.py
docs/docs/safire/jailbreaking/__init__.py
docs/docs/safire/jailbreaking/base.py
docs/docs/safire/jailbreaking/pipeline.py
docs/docs/safire/jailbreaking/assigned/__init__.py
docs/docs/safire/jailbreaking/assigned/prompts/__init__.py
docs/docs/safire/jailbreaking/template/__init__.py
docs/docs/safire/jailbreaking/template/concat_attack.py
docs/docs/safire/jailbreaking/template/questions_puzzle_attack.py
docs/docs/safire/jailbreaking/template/system_key_policy_ideas_attack.py
docs/docs/safire/jailbreaking/template/prompts/__init__.py
safire/__init__.py
safire/constants.py
safire/utils.py
safire/evaluation/__init__.py
safire/evaluation/core.py
safire/evaluation/datasets.py
safire/evaluation/judge.py
safire/evaluation/render.py
safire/jailbreaking/__init__.py
safire/jailbreaking/base.py
safire/jailbreaking/pipeline.py
safire/jailbreaking/assigned/__init__.py
safire/jailbreaking/assigned/prompts/__init__.py
safire/jailbreaking/assigned/prompts/emoji_nuclear_weapon_attack.txt
safire/jailbreaking/template/__init__.py
safire/jailbreaking/template/concat_attack.py
safire/jailbreaking/template/questions_puzzle_attack.py
safire/jailbreaking/template/system_key_policy_ideas_attack.py
safire/jailbreaking/template/prompts/__init__.py
safire/jailbreaking/template/prompts/concat_questions.txt
safire/jailbreaking/template/prompts/questions.txt
safire/jailbreaking/template/prompts/test_template.txt
safire/jailbreaking/template/prompts/unsafe_words.txt
safire/jailbreaking/template/prompts/system/system_key_policy_ideas_attack.txt
safire/jailbreaking/template/prompts/user/questions_puzzle_attack.txt
safire/jailbreaking/template/prompts/user/system_key_policy_ideas_attack.txt
safire_py-0.0.6.dist-info/licenses/LICENSE
tests/test_utils.py
safire_py-0.0.6.dist-info/METADATA
safire_py-0.0.6.dist-info/WHEEL
safire_py-0.0.6.dist-info/top_level.txt
safire_py-0.0.6.dist-info/RECORD
