Metadata-Version: 2.4
Name: safire-py
Version: 0.0.6
Summary: Library for testing of language models for jailbreaking
Author-email: Nikita Bakutov <nikitabakutov2008@gmail.com>
License: MIT
Project-URL: Homepage, https://droyti46.github.io/safire/
Project-URL: Repository, https://github.com/droyti46/safire/
Project-URL: Bug Tracker, https://github.com/droyti46/safire/issues
Classifier: Programming Language :: Python :: 3
Classifier: License :: OSI Approved :: MIT License
Classifier: Operating System :: OS Independent
Requires-Python: >=3.9
License-File: LICENSE
Requires-Dist: pandas>=1.5.3
Requires-Dist: tqdm>=4.67.0
Dynamic: license-file
